cijoe/qemu/__init__.py
cijoe/qemu/wrapper.py
cijoe/qemu/auxiliary/__init__.py
cijoe/qemu/auxiliary/cloudinit-debian-meta.meta
cijoe/qemu/auxiliary/cloudinit-debian-user-amd64.user
cijoe/qemu/auxiliary/cloudinit-debian-user-arm64.user
cijoe/qemu/auxiliary/cloudinit-freebsd-meta.meta
cijoe/qemu/auxiliary/cloudinit-freebsd-user.user
cijoe/qemu/configs/__init__.py
cijoe/qemu/configs/debian-bookworm-amd64-kvm.toml
cijoe/qemu/configs/debian-bookworm-arm64-hvf.toml
cijoe/qemu/configs/debian-bullseye-amd64-kvm.toml
cijoe/qemu/configs/default-config.toml
cijoe/qemu/configs/freebsd-13-amd64-kvm.toml
cijoe/qemu/scripts/__init__.py
cijoe/qemu/scripts/build.py
cijoe/qemu/scripts/guest_init_using_bootimage.py
cijoe/qemu/scripts/guest_init_using_cloudinit.py
cijoe/qemu/scripts/guest_kill.py
cijoe/qemu/scripts/guest_start.py
cijoe/qemu/scripts/install.py
cijoe/qemu/selftest/__init__.py
cijoe/qemu/selftest/test_nop.py
cijoe/qemu/workflows/__init__.py
cijoe/qemu/workflows/example-workflow.yaml
cijoe_pkg_qemu-6.1.15.dist-info/LICENSE
cijoe_pkg_qemu-6.1.15.dist-info/METADATA
cijoe_pkg_qemu-6.1.15.dist-info/WHEEL
cijoe_pkg_qemu-6.1.15.dist-info/top_level.txt
cijoe_pkg_qemu-6.1.15.dist-info/RECORD
